{
    "displayName": "My Awesome Game",
    "gameFormats": ["1p", "coop"],

    "logo": "gamelogo.png",

    "images": ["pic1.jpg", "pic2.png"],
    "videos": ["GameTrailer.webm"],

    "info1": ["Genre", "TheGenre"],
    "info2": ["Course", "TheCourse WS20/21"],
    "info3": ["Creators", "First Name, Second Name, Third Name"],
    "info4": ["", ""],

    "moreInfoText": "In this game you engage in an artificial conflict, defined by rules, that results in a quantifiable outcome.\n\nWe created it under these circumstances. This is how we came up with the idea.\n\nThis is more other cool information."
}
